odoo10_addon_mail_optional_autofollow-10.0.1.0.1-py3.8-nspkg.pth
odoo/addons/mail_optional_autofollow/README.rst
odoo/addons/mail_optional_autofollow/__init__.py
odoo/addons/mail_optional_autofollow/__manifest__.py
odoo/addons/mail_optional_autofollow/i18n/ca.po
odoo/addons/mail_optional_autofollow/i18n/de.po
odoo/addons/mail_optional_autofollow/i18n/es.po
odoo/addons/mail_optional_autofollow/i18n/es_CO.po
odoo/addons/mail_optional_autofollow/i18n/fr.po
odoo/addons/mail_optional_autofollow/i18n/hr.po
odoo/addons/mail_optional_autofollow/i18n/it.po
odoo/addons/mail_optional_autofollow/i18n/mail_optional_autofollow.pot
odoo/addons/mail_optional_autofollow/i18n/pt.po
odoo/addons/mail_optional_autofollow/i18n/pt_BR.po
odoo/addons/mail_optional_autofollow/i18n/sl.po
odoo/addons/mail_optional_autofollow/static/description/autofollow.png
odoo/addons/mail_optional_autofollow/static/description/icon.png
odoo/addons/mail_optional_autofollow/tests/__init__.py
odoo/addons/mail_optional_autofollow/tests/test_mail_optional_autofollow.py
odoo/addons/mail_optional_autofollow/wizard/__init__.py
odoo/addons/mail_optional_autofollow/wizard/mail_compose_message.py
odoo/addons/mail_optional_autofollow/wizard/mail_compose_message_view.xml
odoo10_addon_mail_optional_autofollow-10.0.1.0.1.dist-info/METADATA
odoo10_addon_mail_optional_autofollow-10.0.1.0.1.dist-info/WHEEL
odoo10_addon_mail_optional_autofollow-10.0.1.0.1.dist-info/namespace_packages.txt
odoo10_addon_mail_optional_autofollow-10.0.1.0.1.dist-info/top_level.txt
odoo10_addon_mail_optional_autofollow-10.0.1.0.1.dist-info/RECORD
